setup.py
bitsyauth/__init__.py
bitsyauth/factory.py
bitsyauth.egg-info/PKG-INFO
bitsyauth.egg-info/SOURCES.txt
bitsyauth.egg-info/dependency_links.txt
bitsyauth.egg-info/entry_points.txt
bitsyauth.egg-info/not-zip-safe
bitsyauth.egg-info/requires.txt
bitsyauth.egg-info/top_level.txt