Metadata-Version: 1.0
Name: bitsyauth
Version: 0.1.2
Summary: form + digest auth middleware
Home-page: http://k0s.org/hg/bitsyauth
Author: Jeff Hammel
Author-email: k0scist@gmail.com
License: GPL
Keywords: auth
Platform: UNKNOWN
